{
  "id": "9221133",
  "name": "نرمين السيد احمد على شتا",
  "semester": "Final - Fall",
  "academicYear": "2025/2026",
  "exams": [
    {
      "courseCode": "DNT321E",
      "courseName": "Advanced Removable Prosthodontics",
      "examStartISO": null,
      "examEndISO": null,
      "detailsAvailable": false,
      "countdownHours": null,
      "location": null,
      "seat": null,
      "room": null,
      "building": null
    },
    {
      "courseCode": "DNT411",
      "courseName": "CAD CAM in Prosthodontics : Digitization",
      "examStartISO": null,
      "examEndISO": null,
      "detailsAvailable": false,
      "countdownHours": null,
      "location": null,
      "seat": null,
      "room": null,
      "building": null
    },
    {
      "courseCode": "DNT412",
      "courseName": "Applied Partial Removable Prosthodontics (1)",
      "examStartISO": null,
      "examEndISO": null,
      "detailsAvailable": false,
      "countdownHours": null,
      "location": null,
      "seat": null,
      "room": null,
      "building": null
    },
    {
      "courseCode": "DNT413",
      "courseName": "Oral Pathology",
      "examStartISO": null,
      "examEndISO": null,
      "detailsAvailable": false,
      "countdownHours": null,
      "location": null,
      "seat": null,
      "room": null,
      "building": null
    },
    {
      "courseCode": "DNT414",
      "courseName": "Applied Fixed Prosthodontics (1)",
      "examStartISO": null,
      "examEndISO": null,
      "detailsAvailable": false,
      "countdownHours": null,
      "location": null,
      "seat": null,
      "room": null,
      "building": null
    }
  ],
  "nextExam": null
}