{
  "id": "9231388",
  "name": "مريم محمود زكي محمد سالم",
  "semester": "Final - Fall",
  "academicYear": "2025/2026",
  "exams": [
    {
      "courseCode": "DNT215",
      "courseName": "Dental Morphology & Occlusion Technology",
      "examStartISO": null,
      "examEndISO": null,
      "detailsAvailable": false,
      "countdownHours": null,
      "location": null,
      "seat": null,
      "room": null,
      "building": null
    },
    {
      "courseCode": "DNT311",
      "courseName": "Fixed Prosthodontics Technology (1)",
      "examStartISO": null,
      "examEndISO": null,
      "detailsAvailable": false,
      "countdownHours": null,
      "location": null,
      "seat": null,
      "room": null,
      "building": null
    },
    {
      "courseCode": "DNT312",
      "courseName": "Esthetic Prosthodontics Technology (1)",
      "examStartISO": null,
      "examEndISO": null,
      "detailsAvailable": false,
      "countdownHours": null,
      "location": null,
      "seat": null,
      "room": null,
      "building": null
    },
    {
      "courseCode": "DNT313",
      "courseName": "Dental Implants Technology",
      "examStartISO": null,
      "examEndISO": null,
      "detailsAvailable": false,
      "countdownHours": null,
      "location": null,
      "seat": null,
      "room": null,
      "building": null
    },
    {
      "courseCode": "DNT314",
      "courseName": "Dental Impression Materials Practices",
      "examStartISO": null,
      "examEndISO": null,
      "detailsAvailable": false,
      "countdownHours": null,
      "location": null,
      "seat": null,
      "room": null,
      "building": null
    },
    {
      "courseCode": "GEN402",
      "courseName": "Creativity and Critical Thinking",
      "examStartISO": null,
      "examEndISO": null,
      "detailsAvailable": false,
      "countdownHours": null,
      "location": null,
      "seat": null,
      "room": null,
      "building": null
    }
  ],
  "nextExam": null
}